asarapi/__init__.py
asarapi/catalog.py
asarapi/certs.pem
asarapi/cli.py
asarapi/download.py
asarapi-0.6.dist-info/METADATA
asarapi-0.6.dist-info/RECORD
asarapi-0.6.dist-info/WHEEL
asarapi-0.6.dist-info/entry_points.txt
asarapi-0.6.dist-info/top_level.txt
