Metadata-Version: 2.1
Name: asarapi
Version: 0.6
Summary: Search and download ERS-1, ERS-2, and Envisat products.
Home-page: https://github.com/yannforget/asarapi
Author: Yann Forget
Author-email: yannforget@mailbox.org
License: UNKNOWN
Keywords: earth observation,gis,remote sensing
Platform: UNKNOWN
Classifier: Development Status :: 3 - Alpha
Classifier: Intended Audience :: Developers
Classifier: Intended Audience :: Science/Research
Classifier: Topic :: Scientific/Engineering :: GIS
Classifier: License :: OSI Approved :: MIT License
Classifier: Programming Language :: Python :: 3
Classifier: Programming Language :: Python :: 3.5
Classifier: Programming Language :: Python :: 3.6
Classifier: Programming Language :: Python :: 3.7
Requires-Dist: requests
Requires-Dist: click
Requires-Dist: pandas
Requires-Dist: tqdm
Requires-Dist: shapely
Requires-Dist: appdirs
Requires-Dist: bs4
